alignunformeval/__init__.py
alignunformeval/eval.py
alignunformeval/stsb.py
alignunformeval/tmup.py
alignunformeval-0.0.1.1.dist-info/WHEEL
alignunformeval-0.0.1.1.dist-info/METADATA
alignunformeval-0.0.1.1.dist-info/RECORD
