Metadata-Version: 2.1
Name: alignunformeval
Version: 0.0.1.1
Summary: This is a python tool to evaluate alignment and uniformity of sentence embedding
Home-page: https://github.com/akiFQC/AlignUnformEval
Author: akiFQC
Author-email: yakaredori@gmail.com
Requires-Python: >=3.8,<3.11
Classifier: Programming Language :: Python :: 3
Classifier: Programming Language :: Python :: 3.10
Classifier: Programming Language :: Python :: 3.8
Classifier: Programming Language :: Python :: 3.9
Requires-Dist: pandas (>=1.3.5,<2.0.0)
Requires-Dist: scipy (>=1.7.3,<2.0.0)
Project-URL: Repository, https://github.com/akiFQC/AlignUnformEval
